{"status":1,"msg":"操作成功","res":{"total":659,"per_page":60,"current_page":1,"last_page":11,"data":[{"iconID":2712,"iconName":"WYelement150","iconNameEn":"","width":2438,"height":1835,"iconStyleID":3,"iconStyleCatID":6,"styleCatName":"文艺风","styleCatNameEn":"life","styleName":"元素","styleNameEn":"element","artistAvatar":"b790f792-12e9-410f-99c6-bb391ea0cf2c.png","artistName":"小洋丁插画","artistID":1,"iconType":0,"iconAction":0,"iconActionName":null,"iconActionNameEn":null,"iconPath":"ceaac011-5c52-41d8-9209-44cf8593b019.png","iconSvgPath":"/uploads/eps/icons/wenyi/WYelement150.eps","iconSvg2Path":"/uploads/newSvgs/icons/wenyi/WYelement150.svg","addTime":1636097910,"iconCat":0,"iconCategory":23,"iconCategoryName":"科技","iconCategoryNameEn":"","iconGender":0,"iconGroupID":0,"iconGroupName":null,"iconGroupNameEn":null,"needVip":1,"keywords":[],"keywordsStr":"","keywordsEn":[],"keywordsStrEn":"","width2":300,"height2":225.79983593109105},{"iconID":2788,"iconName":"WYelement111","iconNameEn":"","width":1707,"height":1182,"iconStyleID":3,"iconStyleCatID":6,"styleCatName":"文艺风","styleCatNameEn":"life","styleName":"元素","styleNameEn":"element","artistAvatar":"b790f792-12e9-410f-99c6-bb391ea0cf2c.png","artistName":"小洋丁插画","artistID":1,"iconType":0,"iconAction":0,"iconActionName":null,"iconActionNameEn":null,"iconPath":"d6d0a4f5-06df-4132-9122-7032e9a18a42.png","iconSvgPath":"/uploads/eps/icons/wenyi/WYelement111.eps","iconSvg2Path":"/uploads/newSvgs/icons/wenyi/WYelement111.svg","addTime":1636097975,"iconCat":0,"iconCategory":16,"iconCategoryName":"商务","iconCategoryNameEn":"business","iconGender":0,"iconGroupID":0,"iconGroupName":null,"iconGroupNameEn":null,"needVip":1,"keywords":[],"keywordsStr":"","keywordsEn":[],"keywordsStrEn":"","width2":300,"height2":207.73286467486818},{"iconID":2493,"iconName":"WYelement138","iconNameEn":"","width":2339,"height":620,"iconStyleID":3,"iconStyleCatID":6,"styleCatName":"文艺风","styleCatNameEn":"life","styleName":"元素","styleNameEn":"element","artistAvatar":"b790f792-12e9-410f-99c6-bb391ea0cf2c.png","artistName":"小洋丁插画","artistID":1,"iconType":0,"iconAction":0,"iconActionName":null,"iconActionNameEn":null,"iconPath":"1e1d36b7-0b85-4b9f-b803-d069052c0014.png","iconSvgPath":"/uploads/eps/icons/wenyi/WYelement138.eps","iconSvg2Path":"/uploads/newSvgs/icons/wenyi/WYelement138.svg","addTime":1636097705,"iconCat":0,"iconCategory":16,"iconCategoryName":"商务","iconCategoryNameEn":"business","iconGender":0,"iconGroupID":0,"iconGroupName":null,"iconGroupNameEn":null,"needVip":1,"keywords":[],"keywordsStr":"","keywordsEn":[],"keywordsStrEn":"","width2":300,"height2":79.52116289012399},{"iconID":2494,"iconName":"WYelement122","iconNameEn":"","width":1750,"height":1058,"iconStyleID":3,"iconStyleCatID":6,"styleCatName":"文艺风","styleCatNameEn":"life","styleName":"元素","styleNameEn":"element","artistAvatar":"b790f792-12e9-410f-99c6-bb391ea0cf2c.png","artistName":"小洋丁插画","artistID":1,"iconType":0,"iconAction":0,"iconActionName":null,"iconActionNameEn":null,"iconPath":"52501c54-e838-4c53-8abd-5b8dbd4e457b.png","iconSvgPath":"/uploads/eps/icons/wenyi/WYelement122.eps","iconSvg2Path":"/uploads/newSvgs/icons/wenyi/WYelement122.svg","addTime":1636097705,"iconCat":0,"iconCategory":16,"iconCategoryName":"商务","iconCategoryNameEn":"business","iconGender":0,"iconGroupID":0,"iconGroupName":null,"iconGroupNameEn":null,"needVip":1,"keywords":[],"keywordsStr":"","keywordsEn":[],"keywordsStrEn":"","width2":300,"height2":181.37142857142857},{"iconID":2495,"iconName":"WYelement140","iconNameEn":"","width":2339,"height":600,"iconStyleID":3,"iconStyleCatID":6,"styleCatName":"文艺风","styleCatNameEn":"life","styleName":"元素","styleNameEn":"element","artistAvatar":"b790f792-12e9-410f-99c6-bb391ea0cf2c.png","artistName":"小洋丁插画","artistID":1,"iconType":0,"iconAction":0,"iconActionName":null,"iconActionNameEn":null,"iconPath":"a28d6167-0f46-4fd5-955a-0c0e793c5a12.png","iconSvgPath":"/uploads/eps/icons/wenyi/WYelement140.eps","iconSvg2Path":"/uploads/newSvgs/icons/wenyi/WYelement140.svg","addTime":1636097705,"iconCat":0,"iconCategory":16,"iconCategoryName":"商务","iconCategoryNameEn":"business","iconGender":0,"iconGroupID":0,"iconGroupName":null,"iconGroupNameEn":null,"needVip":1,"keywords":[],"keywordsStr":"","keywordsEn":[],"keywordsStrEn":"","width2":300,"height2":76.95596408721676},{"iconID":2496,"iconName":"WYelement115","iconNameEn":"","width":1951,"height":1299,"iconStyleID":3,"iconStyleCatID":6,"styleCatName":"文艺风","styleCatNameEn":"life","styleName":"元素","styleNameEn":"element","artistAvatar":"b790f792-12e9-410f-99c6-bb391ea0cf2c.png","artistName":"小洋丁插画","artistID":1,"iconType":0,"iconAction":0,"iconActionName":null,"iconActionNameEn":null,"iconPath":"2675d07d-a4e3-4d6b-9955-45236fbfc2a6.png","iconSvgPath":"/uploads/eps/icons/wenyi/WYelement115.eps","iconSvg2Path":"/uploads/newSvgs/icons/wenyi/WYelement115.svg","addTime":1636097705,"iconCat":0,"iconCategory":16,"iconCategoryName":"商务","iconCategoryNameEn":"business","iconGender":0,"iconGroupID":0,"iconGroupName":null,"iconGroupNameEn":null,"needVip":1,"keywords":[],"keywordsStr":"","keywordsEn":[],"keywordsStrEn":"","width2":300,"height2":199.74372116863148},{"iconID":2497,"iconName":"WYelement124","iconNameEn":"","width":1749,"height":1053,"iconStyleID":3,"iconStyleCatID":6,"styleCatName":"文艺风","styleCatNameEn":"life","styleName":"元素","styleNameEn":"element","artistAvatar":"b790f792-12e9-410f-99c6-bb391ea0cf2c.png","artistName":"小洋丁插画","artistID":1,"iconType":0,"iconAction":0,"iconActionName":null,"iconActionNameEn":null,"iconPath":"bcaeda1f-012f-4881-aa71-13bba53daeea.png","iconSvgPath":"/uploads/eps/icons/wenyi/WYelement124.eps","iconSvg2Path":"/uploads/newSvgs/icons/wenyi/WYelement124.svg","addTime":1636097705,"iconCat":0,"iconCategory":16,"iconCategoryName":"商务","iconCategoryNameEn":"business","iconGender":0,"iconGroupID":0,"iconGroupName":null,"iconGroupNameEn":null,"needVip":1,"keywords":[],"keywordsStr":"","keywordsEn":[],"keywordsStrEn":"","width2":300,"height2":180.61749571183535},{"iconID":2498,"iconName":"WYelement37","iconNameEn":"","width":2334,"height":1621,"iconStyleID":3,"iconStyleCatID":6,"styleCatName":"文艺风","styleCatNameEn":"life","styleName":"元素","styleNameEn":"element","artistAvatar":"b790f792-12e9-410f-99c6-bb391ea0cf2c.png","artistName":"小洋丁插画","artistID":1,"iconType":0,"iconAction":0,"iconActionName":null,"iconActionNameEn":null,"iconPath":"ab8a8438-8c8e-4d1c-a01b-d016d7ce6b1f.png","iconSvgPath":"/uploads/eps/icons/wenyi/WYelement37.eps","iconSvg2Path":"/uploads/newSvgs/icons/wenyi/WYelement37.svg","addTime":1636097705,"iconCat":0,"iconCategory":16,"iconCategoryName":"商务","iconCategoryNameEn":"business","iconGender":0,"iconGroupID":0,"iconGroupName":null,"iconGroupNameEn":null,"needVip":1,"keywords":[],"keywordsStr":"","keywordsEn":[],"keywordsStrEn":"","width2":300,"height2":208.3547557840617},{"iconID":2499,"iconName":"WYelement31","iconNameEn":"","width":2126,"height":1973,"iconStyleID":3,"iconStyleCatID":6,"styleCatName":"文艺风","styleCatNameEn":"life","styleName":"元素","styleNameEn":"element","artistAvatar":"b790f792-12e9-410f-99c6-bb391ea0cf2c.png","artistName":"小洋丁插画","artistID":1,"iconType":0,"iconAction":0,"iconActionName":null,"iconActionNameEn":null,"iconPath":"dc3b4c5e-1c2e-4dd6-a8ff-f9deb37f517c.png","iconSvgPath":"/uploads/eps/icons/wenyi/WYelement31.eps","iconSvg2Path":"/uploads/newSvgs/icons/wenyi/WYelement31.svg","addTime":1636097705,"iconCat":0,"iconCategory":16,"iconCategoryName":"商务","iconCategoryNameEn":"business","iconGender":0,"iconGroupID":0,"iconGroupName":null,"iconGroupNameEn":null,"needVip":1,"keywords":[],"keywordsStr":"","keywordsEn":[],"keywordsStrEn":"","width2":300,"height2":278.4101599247413},{"iconID":2500,"iconName":"WYelement92","iconNameEn":"","width":1965,"height":2537,"iconStyleID":3,"iconStyleCatID":6,"styleCatName":"文艺风","styleCatNameEn":"life","styleName":"元素","styleNameEn":"element","artistAvatar":"b790f792-12e9-410f-99c6-bb391ea0cf2c.png","artistName":"小洋丁插画","artistID":1,"iconType":0,"iconAction":0,"iconActionName":null,"iconActionNameEn":null,"iconPath":"0f09b368-a218-4c8e-8e4c-e8f78f844d3c.png","iconSvgPath":"/uploads/eps/icons/wenyi/WYelement92.eps","iconSvg2Path":"/uploads/newSvgs/icons/wenyi/WYelement92.svg","addTime":1636097705,"iconCat":0,"iconCategory":16,"iconCategoryName":"商务","iconCategoryNameEn":"business","iconGender":0,"iconGroupID":0,"iconGroupName":null,"iconGroupNameEn":null,"needVip":1,"keywords":[],"keywordsStr":"","keywordsEn":[],"keywordsStrEn":"","width2":232.36105636578637,"height2":300},{"iconID":2501,"iconName":"WYelement119","iconNameEn":"","width":2110,"height":2110,"iconStyleID":3,"iconStyleCatID":6,"styleCatName":"文艺风","styleCatNameEn":"life","styleName":"元素","styleNameEn":"element","artistAvatar":"b790f792-12e9-410f-99c6-bb391ea0cf2c.png","artistName":"小洋丁插画","artistID":1,"iconType":0,"iconAction":0,"iconActionName":null,"iconActionNameEn":null,"iconPath":"e9d3856f-efa2-4ae1-ba66-628fea0238f0.png","iconSvgPath":"/uploads/eps/icons/wenyi/WYelement119.eps","iconSvg2Path":"/uploads/newSvgs/icons/wenyi/WYelement119.svg","addTime":1636097705,"iconCat":0,"iconCategory":16,"iconCategoryName":"商务","iconCategoryNameEn":"business","iconGender":0,"iconGroupID":0,"iconGroupName":null,"iconGroupNameEn":null,"needVip":1,"keywords":[],"keywordsStr":"","keywordsEn":[],"keywordsStrEn":"","width2":300,"height2":300},{"iconID":2502,"iconName":"WYelement116","iconNameEn":"","width":2130,"height":1128,"iconStyleID":3,"iconStyleCatID":6,"styleCatName":"文艺风","styleCatNameEn":"life","styleName":"元素","styleNameEn":"element","artistAvatar":"b790f792-12e9-410f-99c6-bb391ea0cf2c.png","artistName":"小洋丁插画","artistID":1,"iconType":0,"iconAction":0,"iconActionName":null,"iconActionNameEn":null,"iconPath":"26c4106f-18fa-4008-840a-279e2d65dc5e.png","iconSvgPath":"/uploads/eps/icons/wenyi/WYelement116.eps","iconSvg2Path":"/uploads/newSvgs/icons/wenyi/WYelement116.svg","addTime":1636097705,"iconCat":0,"iconCategory":16,"iconCategoryName":"商务","iconCategoryNameEn":"business","iconGender":0,"iconGroupID":0,"iconGroupName":null,"iconGroupNameEn":null,"needVip":1,"keywords":[],"keywordsStr":"","keywordsEn":[],"keywordsStrEn":"","width2":300,"height2":158.8732394366197},{"iconID":2503,"iconName":"WYelement141","iconNameEn":"","width":1988,"height":1452,"iconStyleID":3,"iconStyleCatID":6,"styleCatName":"文艺风","styleCatNameEn":"life","styleName":"元素","styleNameEn":"element","artistAvatar":"b790f792-12e9-410f-99c6-bb391ea0cf2c.png","artistName":"小洋丁插画","artistID":1,"iconType":0,"iconAction":0,"iconActionName":null,"iconActionNameEn":null,"iconPath":"63a6ab1a-d52b-47ed-82ae-fddd74d59b47.png","iconSvgPath":"/uploads/eps/icons/wenyi/WYelement141.eps","iconSvg2Path":"/uploads/newSvgs/icons/wenyi/WYelement141.svg","addTime":1636097705,"iconCat":0,"iconCategory":16,"iconCategoryName":"商务","iconCategoryNameEn":"business","iconGender":0,"iconGroupID":0,"iconGroupName":null,"iconGroupNameEn":null,"needVip":1,"keywords":[],"keywordsStr":"","keywordsEn":[],"keywordsStrEn":"","width2":300,"height2":219.11468812877263},{"iconID":2504,"iconName":"WYelement149","iconNameEn":"","width":2512,"height":772,"iconStyleID":3,"iconStyleCatID":6,"styleCatName":"文艺风","styleCatNameEn":"life","styleName":"元素","styleNameEn":"element","artistAvatar":"b790f792-12e9-410f-99c6-bb391ea0cf2c.png","artistName":"小洋丁插画","artistID":1,"iconType":0,"iconAction":0,"iconActionName":null,"iconActionNameEn":null,"iconPath":"4d39d56f-f6a2-497a-9d1e-abc585670475.png","iconSvgPath":"/uploads/eps/icons/wenyi/WYelement149.eps","iconSvg2Path":"/uploads/newSvgs/icons/wenyi/WYelement149.svg","addTime":1636097705,"iconCat":0,"iconCategory":16,"iconCategoryName":"商务","iconCategoryNameEn":"business","iconGender":0,"iconGroupID":0,"iconGroupName":null,"iconGroupNameEn":null,"needVip":1,"keywords":[],"keywordsStr":"","keywordsEn":[],"keywordsStrEn":"","width2":300,"height2":92.19745222929936},{"iconID":2505,"iconName":"WYelement93","iconNameEn":"","width":1443,"height":2615,"iconStyleID":3,"iconStyleCatID":6,"styleCatName":"文艺风","styleCatNameEn":"life","styleName":"元素","styleNameEn":"element","artistAvatar":"b790f792-12e9-410f-99c6-bb391ea0cf2c.png","artistName":"小洋丁插画","artistID":1,"iconType":0,"iconAction":0,"iconActionName":null,"iconActionNameEn":null,"iconPath":"4462df41-b972-4b13-81d3-1adbf65804aa.png","iconSvgPath":"/uploads/eps/icons/wenyi/WYelement93.eps","iconSvg2Path":"/uploads/newSvgs/icons/wenyi/WYelement93.svg","addTime":1636097705,"iconCat":0,"iconCategory":16,"iconCategoryName":"商务","iconCategoryNameEn":"business","iconGender":0,"iconGroupID":0,"iconGroupName":null,"iconGroupNameEn":null,"needVip":1,"keywords":[],"keywordsStr":"","keywordsEn":[],"keywordsStrEn":"","width2":165.54493307839388,"height2":300},{"iconID":2506,"iconName":"WYelement36","iconNameEn":"","width":2334,"height":1621,"iconStyleID":3,"iconStyleCatID":6,"styleCatName":"文艺风","styleCatNameEn":"life","styleName":"元素","styleNameEn":"element","artistAvatar":"b790f792-12e9-410f-99c6-bb391ea0cf2c.png","artistName":"小洋丁插画","artistID":1,"iconType":0,"iconAction":0,"iconActionName":null,"iconActionNameEn":null,"iconPath":"67fd850d-82f2-4fc9-9f96-ec0cfe68618d.png","iconSvgPath":"/uploads/eps/icons/wenyi/WYelement36.eps","iconSvg2Path":"/uploads/newSvgs/icons/wenyi/WYelement36.svg","addTime":1636097705,"iconCat":0,"iconCategory":16,"iconCategoryName":"商务","iconCategoryNameEn":"business","iconGender":0,"iconGroupID":0,"iconGroupName":null,"iconGroupNameEn":null,"needVip":1,"keywords":[],"keywordsStr":"","keywordsEn":[],"keywordsStrEn":"","width2":300,"height2":208.3547557840617},{"iconID":2507,"iconName":"WYelement123","iconNameEn":"","width":1750,"height":1055,"iconStyleID":3,"iconStyleCatID":6,"styleCatName":"文艺风","styleCatNameEn":"life","styleName":"元素","styleNameEn":"element","artistAvatar":"b790f792-12e9-410f-99c6-bb391ea0cf2c.png","artistName":"小洋丁插画","artistID":1,"iconType":0,"iconAction":0,"iconActionName":null,"iconActionNameEn":null,"iconPath":"3209486d-1b48-4092-a2e1-b661266eea7c.png","iconSvgPath":"/uploads/eps/icons/wenyi/WYelement123.eps","iconSvg2Path":"/uploads/newSvgs/icons/wenyi/WYelement123.svg","addTime":1636097705,"iconCat":0,"iconCategory":16,"iconCategoryName":"商务","iconCategoryNameEn":"business","iconGender":0,"iconGroupID":0,"iconGroupName":null,"iconGroupNameEn":null,"needVip":1,"keywords":[],"keywordsStr":"","keywordsEn":[],"keywordsStrEn":"","width2":300,"height2":180.85714285714286},{"iconID":2508,"iconName":"WYelement120","iconNameEn":"","width":1750,"height":1057,"iconStyleID":3,"iconStyleCatID":6,"styleCatName":"文艺风","styleCatNameEn":"life","styleName":"元素","styleNameEn":"element","artistAvatar":"b790f792-12e9-410f-99c6-bb391ea0cf2c.png","artistName":"小洋丁插画","artistID":1,"iconType":0,"iconAction":0,"iconActionName":null,"iconActionNameEn":null,"iconPath":"f203caa0-8a76-4337-92ed-c94c0705db32.png","iconSvgPath":"/uploads/eps/icons/wenyi/WYelement120.eps","iconSvg2Path":"/uploads/newSvgs/icons/wenyi/WYelement120.svg","addTime":1636097705,"iconCat":0,"iconCategory":16,"iconCategoryName":"商务","iconCategoryNameEn":"business","iconGender":0,"iconGroupID":0,"iconGroupName":null,"iconGroupNameEn":null,"needVip":1,"keywords":[],"keywordsStr":"","keywordsEn":[],"keywordsStrEn":"","width2":300,"height2":181.2},{"iconID":2509,"iconName":"WYelement121","iconNameEn":"","width":1750,"height":1055,"iconStyleID":3,"iconStyleCatID":6,"styleCatName":"文艺风","styleCatNameEn":"life","styleName":"元素","styleNameEn":"element","artistAvatar":"b790f792-12e9-410f-99c6-bb391ea0cf2c.png","artistName":"小洋丁插画","artistID":1,"iconType":0,"iconAction":0,"iconActionName":null,"iconActionNameEn":null,"iconPath":"d6f82cac-d9ca-4609-be10-468e5b92dab6.png","iconSvgPath":"/uploads/eps/icons/wenyi/WYelement121.eps","iconSvg2Path":"/uploads/newSvgs/icons/wenyi/WYelement121.svg","addTime":1636097705,"iconCat":0,"iconCategory":16,"iconCategoryName":"商务","iconCategoryNameEn":"business","iconGender":0,"iconGroupID":0,"iconGroupName":null,"iconGroupNameEn":null,"needVip":1,"keywords":[],"keywordsStr":"","keywordsEn":[],"keywordsStrEn":"","width2":300,"height2":180.85714285714286},{"iconID":2510,"iconName":"WYelement264","iconNameEn":"","width":2160,"height":1272,"iconStyleID":3,"iconStyleCatID":6,"styleCatName":"文艺风","styleCatNameEn":"life","styleName":"元素","styleNameEn":"element","artistAvatar":"b790f792-12e9-410f-99c6-bb391ea0cf2c.png","artistName":"小洋丁插画","artistID":1,"iconType":0,"iconAction":0,"iconActionName":null,"iconActionNameEn":null,"iconPath":"44162931-ff65-4c4f-8031-1cece3d6eba0.png","iconSvgPath":"/uploads/eps/icons/wenyi/WYelement264.eps","iconSvg2Path":"/uploads/newSvgs/icons/wenyi/WYelement264.svg","addTime":1636097705,"iconCat":0,"iconCategory":16,"iconCategoryName":"商务","iconCategoryNameEn":"business","iconGender":0,"iconGroupID":0,"iconGroupName":null,"iconGroupNameEn":null,"needVip":1,"keywords":[],"keywordsStr":"","keywordsEn":[],"keywordsStrEn":"","width2":300,"height2":176.66666666666666},{"iconID":2511,"iconName":"WYelement263","iconNameEn":"","width":2373,"height":1298,"iconStyleID":3,"iconStyleCatID":6,"styleCatName":"文艺风","styleCatNameEn":"life","styleName":"元素","styleNameEn":"element","artistAvatar":"b790f792-12e9-410f-99c6-bb391ea0cf2c.png","artistName":"小洋丁插画","artistID":1,"iconType":0,"iconAction":0,"iconActionName":null,"iconActionNameEn":null,"iconPath":"a8c54115-4fc5-422c-b459-7c0efb55dd7e.png","iconSvgPath":"/uploads/eps/icons/wenyi/WYelement263.eps","iconSvg2Path":"/uploads/newSvgs/icons/wenyi/WYelement263.svg","addTime":1636097705,"iconCat":0,"iconCategory":16,"iconCategoryName":"商务","iconCategoryNameEn":"business","iconGender":0,"iconGroupID":0,"iconGroupName":null,"iconGroupNameEn":null,"needVip":1,"keywords":[],"keywordsStr":"","keywordsEn":[],"keywordsStrEn":"","width2":300,"height2":164.0960809102402},{"iconID":2512,"iconName":"WYelement248","iconNameEn":"","width":1731,"height":2466,"iconStyleID":3,"iconStyleCatID":6,"styleCatName":"文艺风","styleCatNameEn":"life","styleName":"元素","styleNameEn":"element","artistAvatar":"b790f792-12e9-410f-99c6-bb391ea0cf2c.png","artistName":"小洋丁插画","artistID":1,"iconType":0,"iconAction":0,"iconActionName":null,"iconActionNameEn":null,"iconPath":"b676a7b9-fad9-4bc5-8622-fc9df49797ee.png","iconSvgPath":"/uploads/eps/icons/wenyi/WYelement248.eps","iconSvg2Path":"/uploads/newSvgs/icons/wenyi/WYelement248.svg","addTime":1636097705,"iconCat":0,"iconCategory":18,"iconCategoryName":"教育","iconCategoryNameEn":"educate","iconGender":0,"iconGroupID":0,"iconGroupName":null,"iconGroupNameEn":null,"needVip":1,"keywords":[],"keywordsStr":"","keywordsEn":[],"keywordsStrEn":"","width2":210.5839416058394,"height2":300},{"iconID":2513,"iconName":"WYelement254","iconNameEn":"","width":1582,"height":2161,"iconStyleID":3,"iconStyleCatID":6,"styleCatName":"文艺风","styleCatNameEn":"life","styleName":"元素","styleNameEn":"element","artistAvatar":"b790f792-12e9-410f-99c6-bb391ea0cf2c.png","artistName":"小洋丁插画","artistID":1,"iconType":0,"iconAction":0,"iconActionName":null,"iconActionNameEn":null,"iconPath":"1e3d2336-169a-4f34-9c9b-1f1682acf8c5.png","iconSvgPath":"/uploads/eps/icons/wenyi/WYelement254.eps","iconSvg2Path":"/uploads/newSvgs/icons/wenyi/WYelement254.svg","addTime":1636097705,"iconCat":0,"iconCategory":17,"iconCategoryName":"问卷","iconCategoryNameEn":"","iconGender":0,"iconGroupID":0,"iconGroupName":null,"iconGroupNameEn":null,"needVip":1,"keywords":[],"keywordsStr":"","keywordsEn":[],"keywordsStrEn":"","width2":219.6205460434984,"height2":300},{"iconID":2514,"iconName":"WYelement265","iconNameEn":"","width":1982,"height":1332,"iconStyleID":3,"iconStyleCatID":6,"styleCatName":"文艺风","styleCatNameEn":"life","styleName":"元素","styleNameEn":"element","artistAvatar":"b790f792-12e9-410f-99c6-bb391ea0cf2c.png","artistName":"小洋丁插画","artistID":1,"iconType":0,"iconAction":0,"iconActionName":null,"iconActionNameEn":null,"iconPath":"23b5b1b9-0f6e-4bf4-8ba7-f63435e84000.png","iconSvgPath":"/uploads/eps/icons/wenyi/WYelement265.eps","iconSvg2Path":"/uploads/newSvgs/icons/wenyi/WYelement265.svg","addTime":1636097705,"iconCat":0,"iconCategory":16,"iconCategoryName":"商务","iconCategoryNameEn":"business","iconGender":0,"iconGroupID":0,"iconGroupName":null,"iconGroupNameEn":null,"needVip":1,"keywords":[],"keywordsStr":"","keywordsEn":[],"keywordsStrEn":"","width2":300,"height2":201.61453077699295},{"iconID":2515,"iconName":"WYelement267_1","iconNameEn":"","width":2476,"height":1591,"iconStyleID":3,"iconStyleCatID":6,"styleCatName":"文艺风","styleCatNameEn":"life","styleName":"元素","styleNameEn":"element","artistAvatar":"b790f792-12e9-410f-99c6-bb391ea0cf2c.png","artistName":"小洋丁插画","artistID":1,"iconType":0,"iconAction":0,"iconActionName":null,"iconActionNameEn":null,"iconPath":"f79407a4-214b-4837-86f0-82048f89e219.png","iconSvgPath":"/uploads/eps/icons/wenyi/WYelement267_1.eps","iconSvg2Path":"/uploads/newSvgs/icons/wenyi/WYelement267_1.svg","addTime":1636097705,"iconCat":0,"iconCategory":16,"iconCategoryName":"商务","iconCategoryNameEn":"business","iconGender":0,"iconGroupID":0,"iconGroupName":null,"iconGroupNameEn":null,"needVip":1,"keywords":[],"keywordsStr":"","keywordsEn":[],"keywordsStrEn":"","width2":300,"height2":192.77059773828756},{"iconID":2516,"iconName":"WYelement267","iconNameEn":"","width":2253,"height":1216,"iconStyleID":3,"iconStyleCatID":6,"styleCatName":"文艺风","styleCatNameEn":"life","styleName":"元素","styleNameEn":"element","artistAvatar":"b790f792-12e9-410f-99c6-bb391ea0cf2c.png","artistName":"小洋丁插画","artistID":1,"iconType":0,"iconAction":0,"iconActionName":null,"iconActionNameEn":null,"iconPath":"ef12f8b3-84dd-46c5-8a1f-b1ce99603e2e.png","iconSvgPath":"/uploads/eps/icons/wenyi/WYelement267.eps","iconSvg2Path":"/uploads/newSvgs/icons/wenyi/WYelement267.svg","addTime":1636097705,"iconCat":0,"iconCategory":16,"iconCategoryName":"商务","iconCategoryNameEn":"business","iconGender":0,"iconGroupID":0,"iconGroupName":null,"iconGroupNameEn":null,"needVip":1,"keywords":[],"keywordsStr":"","keywordsEn":[],"keywordsStrEn":"","width2":300,"height2":161.91744340878827},{"iconID":2517,"iconName":"WYelement274","iconNameEn":"","width":2510,"height":1670,"iconStyleID":3,"iconStyleCatID":6,"styleCatName":"文艺风","styleCatNameEn":"life","styleName":"元素","styleNameEn":"element","artistAvatar":"b790f792-12e9-410f-99c6-bb391ea0cf2c.png","artistName":"小洋丁插画","artistID":1,"iconType":0,"iconAction":0,"iconActionName":null,"iconActionNameEn":null,"iconPath":"5fa22b9d-0275-410f-8ebd-b4945ed87098.png","iconSvgPath":"/uploads/eps/icons/wenyi/WYelement274.eps","iconSvg2Path":"/uploads/newSvgs/icons/wenyi/WYelement274.svg","addTime":1636097705,"iconCat":0,"iconCategory":16,"iconCategoryName":"商务","iconCategoryNameEn":"business","iconGender":0,"iconGroupID":0,"iconGroupName":null,"iconGroupNameEn":null,"needVip":1,"keywords":[],"keywordsStr":"","keywordsEn":[],"keywordsStrEn":"","width2":300,"height2":199.601593625498},{"iconID":2518,"iconName":"WYelement270","iconNameEn":"","width":2140,"height":1438,"iconStyleID":3,"iconStyleCatID":6,"styleCatName":"文艺风","styleCatNameEn":"life","styleName":"元素","styleNameEn":"element","artistAvatar":"b790f792-12e9-410f-99c6-bb391ea0cf2c.png","artistName":"小洋丁插画","artistID":1,"iconType":0,"iconAction":0,"iconActionName":null,"iconActionNameEn":null,"iconPath":"0c959b4c-c8c0-4427-8f0c-8b520942c6da.png","iconSvgPath":"/uploads/eps/icons/wenyi/WYelement270.eps","iconSvg2Path":"/uploads/newSvgs/icons/wenyi/WYelement270.svg","addTime":1636097705,"iconCat":0,"iconCategory":16,"iconCategoryName":"商务","iconCategoryNameEn":"business","iconGender":0,"iconGroupID":0,"iconGroupName":null,"iconGroupNameEn":null,"needVip":1,"keywords":[],"keywordsStr":"","keywordsEn":[],"keywordsStrEn":"","width2":300,"height2":201.58878504672896},{"iconID":2519,"iconName":"WYelement268","iconNameEn":"","width":2310,"height":1358,"iconStyleID":3,"iconStyleCatID":6,"styleCatName":"文艺风","styleCatNameEn":"life","styleName":"元素","styleNameEn":"element","artistAvatar":"b790f792-12e9-410f-99c6-bb391ea0cf2c.png","artistName":"小洋丁插画","artistID":1,"iconType":0,"iconAction":0,"iconActionName":null,"iconActionNameEn":null,"iconPath":"50ef5e12-d3ee-4460-981f-0720484e805b.png","iconSvgPath":"/uploads/eps/icons/wenyi/WYelement268.eps","iconSvg2Path":"/uploads/newSvgs/icons/wenyi/WYelement268.svg","addTime":1636097705,"iconCat":0,"iconCategory":16,"iconCategoryName":"商务","iconCategoryNameEn":"business","iconGender":0,"iconGroupID":0,"iconGroupName":null,"iconGroupNameEn":null,"needVip":1,"keywords":[],"keywordsStr":"","keywordsEn":[],"keywordsStrEn":"","width2":300,"height2":176.36363636363637},{"iconID":2520,"iconName":"WYelement279","iconNameEn":"","width":2728,"height":1183,"iconStyleID":3,"iconStyleCatID":6,"styleCatName":"文艺风","styleCatNameEn":"life","styleName":"元素","styleNameEn":"element","artistAvatar":"b790f792-12e9-410f-99c6-bb391ea0cf2c.png","artistName":"小洋丁插画","artistID":1,"iconType":0,"iconAction":0,"iconActionName":null,"iconActionNameEn":null,"iconPath":"5c7e5815-6546-46c7-92e2-79c4560f7cbb.png","iconSvgPath":"/uploads/eps/icons/wenyi/WYelement279.eps","iconSvg2Path":"/uploads/newSvgs/icons/wenyi/WYelement279.svg","addTime":1636097705,"iconCat":0,"iconCategory":16,"iconCategoryName":"商务","iconCategoryNameEn":"business","iconGender":0,"iconGroupID":0,"iconGroupName":null,"iconGroupNameEn":null,"needVip":1,"keywords":[],"keywordsStr":"","keywordsEn":[],"keywordsStrEn":"","width2":300,"height2":130.09530791788856},{"iconID":2521,"iconName":"WYelement292","iconNameEn":"","width":2318,"height":1644,"iconStyleID":3,"iconStyleCatID":6,"styleCatName":"文艺风","styleCatNameEn":"life","styleName":"元素","styleNameEn":"element","artistAvatar":"b790f792-12e9-410f-99c6-bb391ea0cf2c.png","artistName":"小洋丁插画","artistID":1,"iconType":0,"iconAction":0,"iconActionName":null,"iconActionNameEn":null,"iconPath":"faa59726-607b-4c6f-a457-afb919d7d160.png","iconSvgPath":"/uploads/eps/icons/wenyi/WYelement292.eps","iconSvg2Path":"/uploads/newSvgs/icons/wenyi/WYelement292.svg","addTime":1636097705,"iconCat":0,"iconCategory":16,"iconCategoryName":"商务","iconCategoryNameEn":"business","iconGender":0,"iconGroupID":0,"iconGroupName":null,"iconGroupNameEn":null,"needVip":1,"keywords":[],"keywordsStr":"","keywordsEn":[],"keywordsStrEn":"","width2":300,"height2":212.76962899050906},{"iconID":2522,"iconName":"WYelement270_1","iconNameEn":"","width":1486,"height":2130,"iconStyleID":3,"iconStyleCatID":6,"styleCatName":"文艺风","styleCatNameEn":"life","styleName":"元素","styleNameEn":"element","artistAvatar":"b790f792-12e9-410f-99c6-bb391ea0cf2c.png","artistName":"小洋丁插画","artistID":1,"iconType":0,"iconAction":0,"iconActionName":null,"iconActionNameEn":null,"iconPath":"1ee6e214-75d7-4002-9f2c-59561007d905.png","iconSvgPath":"/uploads/eps/icons/wenyi/WYelement270_1.eps","iconSvg2Path":"/uploads/newSvgs/icons/wenyi/WYelement270_1.svg","addTime":1636097705,"iconCat":0,"iconCategory":16,"iconCategoryName":"商务","iconCategoryNameEn":"business","iconGender":0,"iconGroupID":0,"iconGroupName":null,"iconGroupNameEn":null,"needVip":1,"keywords":[],"keywordsStr":"","keywordsEn":[],"keywordsStrEn":"","width2":209.29577464788733,"height2":300},{"iconID":2523,"iconName":"WYelement315","iconNameEn":"","width":1846,"height":1995,"iconStyleID":3,"iconStyleCatID":6,"styleCatName":"文艺风","styleCatNameEn":"life","styleName":"元素","styleNameEn":"element","artistAvatar":"b790f792-12e9-410f-99c6-bb391ea0cf2c.png","artistName":"小洋丁插画","artistID":1,"iconType":0,"iconAction":0,"iconActionName":null,"iconActionNameEn":null,"iconPath":"b9261dca-0b12-49e5-96c4-41aa68b0679a.png","iconSvgPath":"/uploads/eps/icons/wenyi/WYelement315.eps","iconSvg2Path":"/uploads/newSvgs/icons/wenyi/WYelement315.svg","addTime":1636097705,"iconCat":0,"iconCategory":17,"iconCategoryName":"问卷","iconCategoryNameEn":"","iconGender":0,"iconGroupID":0,"iconGroupName":null,"iconGroupNameEn":null,"needVip":1,"keywords":[],"keywordsStr":"","keywordsEn":[],"keywordsStrEn":"","width2":277.593984962406,"height2":300},{"iconID":2524,"iconName":"WYelement300","iconNameEn":"","width":1668,"height":1431,"iconStyleID":3,"iconStyleCatID":6,"styleCatName":"文艺风","styleCatNameEn":"life","styleName":"元素","styleNameEn":"element","artistAvatar":"b790f792-12e9-410f-99c6-bb391ea0cf2c.png","artistName":"小洋丁插画","artistID":1,"iconType":0,"iconAction":0,"iconActionName":null,"iconActionNameEn":null,"iconPath":"129ecbeb-50b1-42eb-937e-29e80ebf20a9.png","iconSvgPath":"/uploads/eps/icons/wenyi/WYelement300.eps","iconSvg2Path":"/uploads/newSvgs/icons/wenyi/WYelement300.svg","addTime":1636097705,"iconCat":0,"iconCategory":16,"iconCategoryName":"商务","iconCategoryNameEn":"business","iconGender":0,"iconGroupID":0,"iconGroupName":null,"iconGroupNameEn":null,"needVip":1,"keywords":[],"keywordsStr":"","keywordsEn":[],"keywordsStrEn":"","width2":300,"height2":257.37410071942446},{"iconID":2525,"iconName":"WYelement275","iconNameEn":"","width":1724,"height":2412,"iconStyleID":3,"iconStyleCatID":6,"styleCatName":"文艺风","styleCatNameEn":"life","styleName":"元素","styleNameEn":"element","artistAvatar":"b790f792-12e9-410f-99c6-bb391ea0cf2c.png","artistName":"小洋丁插画","artistID":1,"iconType":0,"iconAction":0,"iconActionName":null,"iconActionNameEn":null,"iconPath":"5d7e1976-2a66-4b76-abc1-9e43bcbb6f42.png","iconSvgPath":"/uploads/eps/icons/wenyi/WYelement275.eps","iconSvg2Path":"/uploads/newSvgs/icons/wenyi/WYelement275.svg","addTime":1636097705,"iconCat":0,"iconCategory":16,"iconCategoryName":"商务","iconCategoryNameEn":"business","iconGender":0,"iconGroupID":0,"iconGroupName":null,"iconGroupNameEn":null,"needVip":1,"keywords":[],"keywordsStr":"","keywordsEn":[],"keywordsStrEn":"","width2":214.4278606965174,"height2":300},{"iconID":2526,"iconName":"WYelement312","iconNameEn":"","width":2478,"height":1314,"iconStyleID":3,"iconStyleCatID":6,"styleCatName":"文艺风","styleCatNameEn":"life","styleName":"元素","styleNameEn":"element","artistAvatar":"b790f792-12e9-410f-99c6-bb391ea0cf2c.png","artistName":"小洋丁插画","artistID":1,"iconType":0,"iconAction":0,"iconActionName":null,"iconActionNameEn":null,"iconPath":"7e060c6e-7fcf-43c8-9f6b-bb8c4ab0e7b4.png","iconSvgPath":"/uploads/eps/icons/wenyi/WYelement312.eps","iconSvg2Path":"/uploads/newSvgs/icons/wenyi/WYelement312.svg","addTime":1636097705,"iconCat":0,"iconCategory":16,"iconCategoryName":"商务","iconCategoryNameEn":"business","iconGender":0,"iconGroupID":0,"iconGroupName":null,"iconGroupNameEn":null,"needVip":1,"keywords":[],"keywordsStr":"","keywordsEn":[],"keywordsStrEn":"","width2":300,"height2":159.07990314769975},{"iconID":2527,"iconName":"WYelement139","iconNameEn":"","width":2339,"height":600,"iconStyleID":3,"iconStyleCatID":6,"styleCatName":"文艺风","styleCatNameEn":"life","styleName":"元素","styleNameEn":"element","artistAvatar":"b790f792-12e9-410f-99c6-bb391ea0cf2c.png","artistName":"小洋丁插画","artistID":1,"iconType":0,"iconAction":0,"iconActionName":null,"iconActionNameEn":null,"iconPath":"abf34d4e-de05-41e5-b19b-79f022550fa1.png","iconSvgPath":"/uploads/eps/icons/wenyi/WYelement139.eps","iconSvg2Path":"/uploads/newSvgs/icons/wenyi/WYelement139.svg","addTime":1636097705,"iconCat":0,"iconCategory":16,"iconCategoryName":"商务","iconCategoryNameEn":"business","iconGender":0,"iconGroupID":0,"iconGroupName":null,"iconGroupNameEn":null,"needVip":1,"keywords":[],"keywordsStr":"","keywordsEn":[],"keywordsStrEn":"","width2":300,"height2":76.95596408721676},{"iconID":2528,"iconName":"WYelement153","iconNameEn":"","width":2378,"height":1592,"iconStyleID":3,"iconStyleCatID":6,"styleCatName":"文艺风","styleCatNameEn":"life","styleName":"元素","styleNameEn":"element","artistAvatar":"b790f792-12e9-410f-99c6-bb391ea0cf2c.png","artistName":"小洋丁插画","artistID":1,"iconType":0,"iconAction":0,"iconActionName":null,"iconActionNameEn":null,"iconPath":"ef2a9044-c215-469a-96f1-52cff68feaa7.png","iconSvgPath":"/uploads/eps/icons/wenyi/WYelement153.eps","iconSvg2Path":"/uploads/newSvgs/icons/wenyi/WYelement153.svg","addTime":1636097705,"iconCat":0,"iconCategory":16,"iconCategoryName":"商务","iconCategoryNameEn":"business","iconGender":0,"iconGroupID":0,"iconGroupName":null,"iconGroupNameEn":null,"needVip":1,"keywords":[],"keywordsStr":"","keywordsEn":[],"keywordsStrEn":"","width2":300,"height2":200.84104289318756},{"iconID":2529,"iconName":"WYelement152","iconNameEn":"","width":2153,"height":2018,"iconStyleID":3,"iconStyleCatID":6,"styleCatName":"文艺风","styleCatNameEn":"life","styleName":"元素","styleNameEn":"element","artistAvatar":"b790f792-12e9-410f-99c6-bb391ea0cf2c.png","artistName":"小洋丁插画","artistID":1,"iconType":0,"iconAction":0,"iconActionName":null,"iconActionNameEn":null,"iconPath":"2904b0e5-847a-472a-a68d-35aa3b440744.png","iconSvgPath":"/uploads/eps/icons/wenyi/WYelement152.eps","iconSvg2Path":"/uploads/newSvgs/icons/wenyi/WYelement152.svg","addTime":1636097705,"iconCat":0,"iconCategory":16,"iconCategoryName":"商务","iconCategoryNameEn":"business","iconGender":0,"iconGroupID":0,"iconGroupName":null,"iconGroupNameEn":null,"needVip":1,"keywords":[],"keywordsStr":"","keywordsEn":[],"keywordsStrEn":"","width2":300,"height2":281.18903855085927},{"iconID":2530,"iconName":"WYelement154","iconNameEn":"","width":2378,"height":1592,"iconStyleID":3,"iconStyleCatID":6,"styleCatName":"文艺风","styleCatNameEn":"life","styleName":"元素","styleNameEn":"element","artistAvatar":"b790f792-12e9-410f-99c6-bb391ea0cf2c.png","artistName":"小洋丁插画","artistID":1,"iconType":0,"iconAction":0,"iconActionName":null,"iconActionNameEn":null,"iconPath":"7639e1dc-808f-4951-8099-89611c1fc7b4.png","iconSvgPath":"/uploads/eps/icons/wenyi/WYelement154.eps","iconSvg2Path":"/uploads/newSvgs/icons/wenyi/WYelement154.svg","addTime":1636097705,"iconCat":0,"iconCategory":16,"iconCategoryName":"商务","iconCategoryNameEn":"business","iconGender":0,"iconGroupID":0,"iconGroupName":null,"iconGroupNameEn":null,"needVip":1,"keywords":[],"keywordsStr":"","keywordsEn":[],"keywordsStrEn":"","width2":300,"height2":200.84104289318756},{"iconID":2531,"iconName":"WYelement145","iconNameEn":"","width":2512,"height":772,"iconStyleID":3,"iconStyleCatID":6,"styleCatName":"文艺风","styleCatNameEn":"life","styleName":"元素","styleNameEn":"element","artistAvatar":"b790f792-12e9-410f-99c6-bb391ea0cf2c.png","artistName":"小洋丁插画","artistID":1,"iconType":0,"iconAction":0,"iconActionName":null,"iconActionNameEn":null,"iconPath":"53b963b9-a62f-4a92-b9fc-6496f44e7e0d.png","iconSvgPath":"/uploads/eps/icons/wenyi/WYelement145.eps","iconSvg2Path":"/uploads/newSvgs/icons/wenyi/WYelement145.svg","addTime":1636097705,"iconCat":0,"iconCategory":16,"iconCategoryName":"商务","iconCategoryNameEn":"business","iconGender":0,"iconGroupID":0,"iconGroupName":null,"iconGroupNameEn":null,"needVip":1,"keywords":[],"keywordsStr":"","keywordsEn":[],"keywordsStrEn":"","width2":300,"height2":92.19745222929936},{"iconID":2532,"iconName":"WYelement172","iconNameEn":"","width":2656,"height":1324,"iconStyleID":3,"iconStyleCatID":6,"styleCatName":"文艺风","styleCatNameEn":"life","styleName":"元素","styleNameEn":"element","artistAvatar":"b790f792-12e9-410f-99c6-bb391ea0cf2c.png","artistName":"小洋丁插画","artistID":1,"iconType":0,"iconAction":0,"iconActionName":null,"iconActionNameEn":null,"iconPath":"3ae0bc2e-e1cd-4cd0-ae1c-77e8f9b32223.png","iconSvgPath":"/uploads/eps/icons/wenyi/WYelement172.eps","iconSvg2Path":"/uploads/newSvgs/icons/wenyi/WYelement172.svg","addTime":1636097705,"iconCat":0,"iconCategory":16,"iconCategoryName":"商务","iconCategoryNameEn":"business","iconGender":0,"iconGroupID":0,"iconGroupName":null,"iconGroupNameEn":null,"needVip":1,"keywords":[],"keywordsStr":"","keywordsEn":[],"keywordsStrEn":"","width2":300,"height2":149.54819277108433},{"iconID":2533,"iconName":"WYelement144","iconNameEn":"","width":2511,"height":772,"iconStyleID":3,"iconStyleCatID":6,"styleCatName":"文艺风","styleCatNameEn":"life","styleName":"元素","styleNameEn":"element","artistAvatar":"b790f792-12e9-410f-99c6-bb391ea0cf2c.png","artistName":"小洋丁插画","artistID":1,"iconType":0,"iconAction":0,"iconActionName":null,"iconActionNameEn":null,"iconPath":"426396df-cf36-4a36-9a84-d6245ee8e81d.png","iconSvgPath":"/uploads/eps/icons/wenyi/WYelement144.eps","iconSvg2Path":"/uploads/newSvgs/icons/wenyi/WYelement144.svg","addTime":1636097705,"iconCat":0,"iconCategory":16,"iconCategoryName":"商务","iconCategoryNameEn":"business","iconGender":0,"iconGroupID":0,"iconGroupName":null,"iconGroupNameEn":null,"needVip":1,"keywords":[],"keywordsStr":"","keywordsEn":[],"keywordsStrEn":"","width2":300,"height2":92.23416965352449},{"iconID":2534,"iconName":"WYelement155","iconNameEn":"","width":2097,"height":1014,"iconStyleID":3,"iconStyleCatID":6,"styleCatName":"文艺风","styleCatNameEn":"life","styleName":"元素","styleNameEn":"element","artistAvatar":"b790f792-12e9-410f-99c6-bb391ea0cf2c.png","artistName":"小洋丁插画","artistID":1,"iconType":0,"iconAction":0,"iconActionName":null,"iconActionNameEn":null,"iconPath":"f19b237c-ec29-4a9e-9c94-cd9783d33e18.png","iconSvgPath":"/uploads/eps/icons/wenyi/WYelement155.eps","iconSvg2Path":"/uploads/newSvgs/icons/wenyi/WYelement155.svg","addTime":1636097705,"iconCat":0,"iconCategory":16,"iconCategoryName":"商务","iconCategoryNameEn":"business","iconGender":0,"iconGroupID":0,"iconGroupName":null,"iconGroupNameEn":null,"needVip":1,"keywords":[],"keywordsStr":"","keywordsEn":[],"keywordsStrEn":"","width2":300,"height2":145.06437768240343},{"iconID":2535,"iconName":"WYelement175","iconNameEn":"","width":1584,"height":2619,"iconStyleID":3,"iconStyleCatID":6,"styleCatName":"文艺风","styleCatNameEn":"life","styleName":"元素","styleNameEn":"element","artistAvatar":"b790f792-12e9-410f-99c6-bb391ea0cf2c.png","artistName":"小洋丁插画","artistID":1,"iconType":0,"iconAction":0,"iconActionName":null,"iconActionNameEn":null,"iconPath":"442ae78b-b31d-4a75-9be3-da685981ca5e.png","iconSvgPath":"/uploads/eps/icons/wenyi/WYelement175.eps","iconSvg2Path":"/uploads/newSvgs/icons/wenyi/WYelement175.svg","addTime":1636097705,"iconCat":0,"iconCategory":16,"iconCategoryName":"商务","iconCategoryNameEn":"business","iconGender":0,"iconGroupID":0,"iconGroupName":null,"iconGroupNameEn":null,"needVip":1,"keywords":[],"keywordsStr":"","keywordsEn":[],"keywordsStrEn":"","width2":181.44329896907217,"height2":300},{"iconID":2536,"iconName":"WYelement174","iconNameEn":"","width":2657,"height":1323,"iconStyleID":3,"iconStyleCatID":6,"styleCatName":"文艺风","styleCatNameEn":"life","styleName":"元素","styleNameEn":"element","artistAvatar":"b790f792-12e9-410f-99c6-bb391ea0cf2c.png","artistName":"小洋丁插画","artistID":1,"iconType":0,"iconAction":0,"iconActionName":null,"iconActionNameEn":null,"iconPath":"6bc92d6b-aabd-4b2d-a47a-e201c2163118.png","iconSvgPath":"/uploads/eps/icons/wenyi/WYelement174.eps","iconSvg2Path":"/uploads/newSvgs/icons/wenyi/WYelement174.svg","addTime":1636097705,"iconCat":0,"iconCategory":16,"iconCategoryName":"商务","iconCategoryNameEn":"business","iconGender":0,"iconGroupID":0,"iconGroupName":null,"iconGroupNameEn":null,"needVip":1,"keywords":[],"keywordsStr":"","keywordsEn":[],"keywordsStrEn":"","width2":300,"height2":149.37899887090703},{"iconID":2537,"iconName":"WYelement177","iconNameEn":"","width":1583,"height":2619,"iconStyleID":3,"iconStyleCatID":6,"styleCatName":"文艺风","styleCatNameEn":"life","styleName":"元素","styleNameEn":"element","artistAvatar":"b790f792-12e9-410f-99c6-bb391ea0cf2c.png","artistName":"小洋丁插画","artistID":1,"iconType":0,"iconAction":0,"iconActionName":null,"iconActionNameEn":null,"iconPath":"cee763eb-10a7-4e05-af24-296b2ef0d85b.png","iconSvgPath":"/uploads/eps/icons/wenyi/WYelement177.eps","iconSvg2Path":"/uploads/newSvgs/icons/wenyi/WYelement177.svg","addTime":1636097705,"iconCat":0,"iconCategory":16,"iconCategoryName":"商务","iconCategoryNameEn":"business","iconGender":0,"iconGroupID":0,"iconGroupName":null,"iconGroupNameEn":null,"needVip":1,"keywords":[],"keywordsStr":"","keywordsEn":[],"keywordsStrEn":"","width2":181.3287514318442,"height2":300},{"iconID":2538,"iconName":"WYelement183","iconNameEn":"","width":2448,"height":2452,"iconStyleID":3,"iconStyleCatID":6,"styleCatName":"文艺风","styleCatNameEn":"life","styleName":"元素","styleNameEn":"element","artistAvatar":"b790f792-12e9-410f-99c6-bb391ea0cf2c.png","artistName":"小洋丁插画","artistID":1,"iconType":0,"iconAction":0,"iconActionName":null,"iconActionNameEn":null,"iconPath":"da102bc3-6dd4-4aab-81b7-4dd8b47ffabc.png","iconSvgPath":"/uploads/eps/icons/wenyi/WYelement183.eps","iconSvg2Path":"/uploads/newSvgs/icons/wenyi/WYelement183.svg","addTime":1636097705,"iconCat":0,"iconCategory":16,"iconCategoryName":"商务","iconCategoryNameEn":"business","iconGender":0,"iconGroupID":0,"iconGroupName":null,"iconGroupNameEn":null,"needVip":1,"keywords":[],"keywordsStr":"","keywordsEn":[],"keywordsStrEn":"","width2":299.51060358890703,"height2":300},{"iconID":2539,"iconName":"WYelement173","iconNameEn":"","width":2657,"height":1324,"iconStyleID":3,"iconStyleCatID":6,"styleCatName":"文艺风","styleCatNameEn":"life","styleName":"元素","styleNameEn":"element","artistAvatar":"b790f792-12e9-410f-99c6-bb391ea0cf2c.png","artistName":"小洋丁插画","artistID":1,"iconType":0,"iconAction":0,"iconActionName":null,"iconActionNameEn":null,"iconPath":"f1ad09e8-ead5-4cc0-806d-4de88a501446.png","iconSvgPath":"/uploads/eps/icons/wenyi/WYelement173.eps","iconSvg2Path":"/uploads/newSvgs/icons/wenyi/WYelement173.svg","addTime":1636097705,"iconCat":0,"iconCategory":16,"iconCategoryName":"商务","iconCategoryNameEn":"business","iconGender":0,"iconGroupID":0,"iconGroupName":null,"iconGroupNameEn":null,"needVip":1,"keywords":[],"keywordsStr":"","keywordsEn":[],"keywordsStrEn":"","width2":300,"height2":149.49190816710575},{"iconID":2540,"iconName":"WYelement192","iconNameEn":"","width":2492,"height":1308,"iconStyleID":3,"iconStyleCatID":6,"styleCatName":"文艺风","styleCatNameEn":"life","styleName":"元素","styleNameEn":"element","artistAvatar":"b790f792-12e9-410f-99c6-bb391ea0cf2c.png","artistName":"小洋丁插画","artistID":1,"iconType":0,"iconAction":0,"iconActionName":null,"iconActionNameEn":null,"iconPath":"1107583e-8f95-4981-b143-daf1af24dbdd.png","iconSvgPath":"/uploads/eps/icons/wenyi/WYelement192.eps","iconSvg2Path":"/uploads/newSvgs/icons/wenyi/WYelement192.svg","addTime":1636097705,"iconCat":0,"iconCategory":16,"iconCategoryName":"商务","iconCategoryNameEn":"business","iconGender":0,"iconGroupID":0,"iconGroupName":null,"iconGroupNameEn":null,"needVip":1,"keywords":[],"keywordsStr":"","keywordsEn":[],"keywordsStrEn":"","width2":300,"height2":157.46388443017656},{"iconID":2541,"iconName":"WYelement222","iconNameEn":"","width":2112,"height":1554,"iconStyleID":3,"iconStyleCatID":6,"styleCatName":"文艺风","styleCatNameEn":"life","styleName":"元素","styleNameEn":"element","artistAvatar":"b790f792-12e9-410f-99c6-bb391ea0cf2c.png","artistName":"小洋丁插画","artistID":1,"iconType":0,"iconAction":0,"iconActionName":null,"iconActionNameEn":null,"iconPath":"3807deee-71b9-446b-9cfa-947e2a629f17.png","iconSvgPath":"/uploads/eps/icons/wenyi/WYelement222.eps","iconSvg2Path":"/uploads/newSvgs/icons/wenyi/WYelement222.svg","addTime":1636097705,"iconCat":0,"iconCategory":16,"iconCategoryName":"商务","iconCategoryNameEn":"business","iconGender":0,"iconGroupID":0,"iconGroupName":null,"iconGroupNameEn":null,"needVip":1,"keywords":[],"keywordsStr":"","keywordsEn":[],"keywordsStrEn":"","width2":300,"height2":220.73863636363637},{"iconID":2542,"iconName":"WYelement262","iconNameEn":"","width":1433,"height":1933,"iconStyleID":3,"iconStyleCatID":6,"styleCatName":"文艺风","styleCatNameEn":"life","styleName":"元素","styleNameEn":"element","artistAvatar":"b790f792-12e9-410f-99c6-bb391ea0cf2c.png","artistName":"小洋丁插画","artistID":1,"iconType":0,"iconAction":0,"iconActionName":null,"iconActionNameEn":null,"iconPath":"0243e96e-23a1-4bb5-ab27-9212574af1dc.png","iconSvgPath":"/uploads/eps/icons/wenyi/WYelement262.eps","iconSvg2Path":"/uploads/newSvgs/icons/wenyi/WYelement262.svg","addTime":1636097705,"iconCat":0,"iconCategory":16,"iconCategoryName":"商务","iconCategoryNameEn":"business","iconGender":0,"iconGroupID":0,"iconGroupName":null,"iconGroupNameEn":null,"needVip":1,"keywords":[],"keywordsStr":"","keywordsEn":[],"keywordsStrEn":"","width2":222.40041386445938,"height2":300},{"iconID":2543,"iconName":"WYelement185","iconNameEn":"","width":2378,"height":1593,"iconStyleID":3,"iconStyleCatID":6,"styleCatName":"文艺风","styleCatNameEn":"life","styleName":"元素","styleNameEn":"element","artistAvatar":"b790f792-12e9-410f-99c6-bb391ea0cf2c.png","artistName":"小洋丁插画","artistID":1,"iconType":0,"iconAction":0,"iconActionName":null,"iconActionNameEn":null,"iconPath":"a609c1aa-18e9-429f-8924-fc8f137c3e91.png","iconSvgPath":"/uploads/eps/icons/wenyi/WYelement185.eps","iconSvg2Path":"/uploads/newSvgs/icons/wenyi/WYelement185.svg","addTime":1636097705,"iconCat":0,"iconCategory":16,"iconCategoryName":"商务","iconCategoryNameEn":"business","iconGender":0,"iconGroupID":0,"iconGroupName":null,"iconGroupNameEn":null,"needVip":1,"keywords":[],"keywordsStr":"","keywordsEn":[],"keywordsStrEn":"","width2":300,"height2":200.96719932716567},{"iconID":2544,"iconName":"WYelement283","iconNameEn":"","width":2603,"height":1464,"iconStyleID":3,"iconStyleCatID":6,"styleCatName":"文艺风","styleCatNameEn":"life","styleName":"元素","styleNameEn":"element","artistAvatar":"b790f792-12e9-410f-99c6-bb391ea0cf2c.png","artistName":"小洋丁插画","artistID":1,"iconType":0,"iconAction":0,"iconActionName":null,"iconActionNameEn":null,"iconPath":"6f1cc568-f9cb-4c94-a448-221e86085d6a.png","iconSvgPath":"/uploads/eps/icons/wenyi/WYelement283.eps","iconSvg2Path":"/uploads/newSvgs/icons/wenyi/WYelement283.svg","addTime":1636097705,"iconCat":0,"iconCategory":18,"iconCategoryName":"教育","iconCategoryNameEn":"educate","iconGender":0,"iconGroupID":0,"iconGroupName":null,"iconGroupNameEn":null,"needVip":1,"keywords":[],"keywordsStr":"","keywordsEn":[],"keywordsStrEn":"","width2":300,"height2":168.72839031886286},{"iconID":2545,"iconName":"WYelement33","iconNameEn":"","width":1976,"height":2221,"iconStyleID":3,"iconStyleCatID":6,"styleCatName":"文艺风","styleCatNameEn":"life","styleName":"元素","styleNameEn":"element","artistAvatar":"b790f792-12e9-410f-99c6-bb391ea0cf2c.png","artistName":"小洋丁插画","artistID":1,"iconType":0,"iconAction":0,"iconActionName":null,"iconActionNameEn":null,"iconPath":"b444cf56-15f3-4ab9-b3e6-2ffabc745b1f.png","iconSvgPath":"/uploads/eps/icons/wenyi/WYelement33.eps","iconSvg2Path":"/uploads/newSvgs/icons/wenyi/WYelement33.svg","addTime":1636097736,"iconCat":0,"iconCategory":17,"iconCategoryName":"问卷","iconCategoryNameEn":"","iconGender":0,"iconGroupID":0,"iconGroupName":null,"iconGroupNameEn":null,"needVip":1,"keywords":[],"keywordsStr":"","keywordsEn":[],"keywordsStrEn":"","width2":266.9067987393066,"height2":300},{"iconID":2546,"iconName":"WYelement30","iconNameEn":"","width":1976,"height":2221,"iconStyleID":3,"iconStyleCatID":6,"styleCatName":"文艺风","styleCatNameEn":"life","styleName":"元素","styleNameEn":"element","artistAvatar":"b790f792-12e9-410f-99c6-bb391ea0cf2c.png","artistName":"小洋丁插画","artistID":1,"iconType":0,"iconAction":0,"iconActionName":null,"iconActionNameEn":null,"iconPath":"545b0564-569b-402c-8df2-27e17706ab0c.png","iconSvgPath":"/uploads/eps/icons/wenyi/WYelement30.eps","iconSvg2Path":"/uploads/newSvgs/icons/wenyi/WYelement30.svg","addTime":1636097736,"iconCat":0,"iconCategory":17,"iconCategoryName":"问卷","iconCategoryNameEn":"","iconGender":0,"iconGroupID":0,"iconGroupName":null,"iconGroupNameEn":null,"needVip":1,"keywords":[],"keywordsStr":"","keywordsEn":[],"keywordsStrEn":"","width2":266.9067987393066,"height2":300},{"iconID":2547,"iconName":"WYelement42","iconNameEn":"","width":1828,"height":2811,"iconStyleID":3,"iconStyleCatID":6,"styleCatName":"文艺风","styleCatNameEn":"life","styleName":"元素","styleNameEn":"element","artistAvatar":"b790f792-12e9-410f-99c6-bb391ea0cf2c.png","artistName":"小洋丁插画","artistID":1,"iconType":0,"iconAction":0,"iconActionName":null,"iconActionNameEn":null,"iconPath":"7871ad2a-70f6-4155-9f0b-1a6c55b1a7f2.png","iconSvgPath":"/uploads/eps/icons/wenyi/WYelement42.eps","iconSvg2Path":"/uploads/newSvgs/icons/wenyi/WYelement42.svg","addTime":1636097736,"iconCat":0,"iconCategory":17,"iconCategoryName":"问卷","iconCategoryNameEn":"","iconGender":0,"iconGroupID":0,"iconGroupName":null,"iconGroupNameEn":null,"needVip":1,"keywords":[],"keywordsStr":"","keywordsEn":[],"keywordsStrEn":"","width2":195.0907150480256,"height2":300},{"iconID":2548,"iconName":"WYelement110","iconNameEn":"","width":1056,"height":1895,"iconStyleID":3,"iconStyleCatID":6,"styleCatName":"文艺风","styleCatNameEn":"life","styleName":"元素","styleNameEn":"element","artistAvatar":"b790f792-12e9-410f-99c6-bb391ea0cf2c.png","artistName":"小洋丁插画","artistID":1,"iconType":0,"iconAction":0,"iconActionName":null,"iconActionNameEn":null,"iconPath":"636f8d14-9a3b-45c0-8dcc-58f2aa5ae1ee.png","iconSvgPath":"/uploads/eps/icons/wenyi/WYelement110.eps","iconSvg2Path":"/uploads/newSvgs/icons/wenyi/WYelement110.svg","addTime":1636097736,"iconCat":0,"iconCategory":65,"iconCategoryName":"问卷","iconCategoryNameEn":"questionnaire","iconGender":0,"iconGroupID":0,"iconGroupName":null,"iconGroupNameEn":null,"needVip":1,"keywords":[],"keywordsStr":"","keywordsEn":[],"keywordsStrEn":"","width2":167.17678100263853,"height2":300},{"iconID":2549,"iconName":"WYelement43","iconNameEn":"","width":1828,"height":2811,"iconStyleID":3,"iconStyleCatID":6,"styleCatName":"文艺风","styleCatNameEn":"life","styleName":"元素","styleNameEn":"element","artistAvatar":"b790f792-12e9-410f-99c6-bb391ea0cf2c.png","artistName":"小洋丁插画","artistID":1,"iconType":0,"iconAction":0,"iconActionName":null,"iconActionNameEn":null,"iconPath":"65b4d8bb-77b6-47f9-9bb9-bd2558e6cca6.png","iconSvgPath":"/uploads/eps/icons/wenyi/WYelement43.eps","iconSvg2Path":"/uploads/newSvgs/icons/wenyi/WYelement43.svg","addTime":1636097736,"iconCat":0,"iconCategory":17,"iconCategoryName":"问卷","iconCategoryNameEn":"","iconGender":0,"iconGroupID":0,"iconGroupName":null,"iconGroupNameEn":null,"needVip":1,"keywords":[],"keywordsStr":"","keywordsEn":[],"keywordsStrEn":"","width2":195.0907150480256,"height2":300},{"iconID":2550,"iconName":"WYelement32","iconNameEn":"","width":1829,"height":2812,"iconStyleID":3,"iconStyleCatID":6,"styleCatName":"文艺风","styleCatNameEn":"life","styleName":"元素","styleNameEn":"element","artistAvatar":"b790f792-12e9-410f-99c6-bb391ea0cf2c.png","artistName":"小洋丁插画","artistID":1,"iconType":0,"iconAction":0,"iconActionName":null,"iconActionNameEn":null,"iconPath":"9439ae81-8d97-4106-afb4-b35d7d5968cb.png","iconSvgPath":"/uploads/eps/icons/wenyi/WYelement32.eps","iconSvg2Path":"/uploads/newSvgs/icons/wenyi/WYelement32.svg","addTime":1636097736,"iconCat":0,"iconCategory":16,"iconCategoryName":"商务","iconCategoryNameEn":"business","iconGender":0,"iconGroupID":0,"iconGroupName":null,"iconGroupNameEn":null,"needVip":1,"keywords":[],"keywordsStr":"","keywordsEn":[],"keywordsStrEn":"","width2":195.12802275960172,"height2":300}]}}